objectdaddy/__init__.py
objectdaddy/detection.py
objectdaddy/object_detector.py
objectdaddy/mlmodels/__init__.py
objectdaddy/mlmodels/coco.names
objectdaddy/mlmodels/yolov3-tiny.cfg
objectdaddy/mlmodels/yolov3-tiny.weights
objectdaddy-0.0.5.dist-info/LICENSE.md
objectdaddy-0.0.5.dist-info/METADATA
objectdaddy-0.0.5.dist-info/WHEEL
objectdaddy-0.0.5.dist-info/top_level.txt
objectdaddy-0.0.5.dist-info/RECORD
