Metadata-Version: 2.1
Name: objectdaddy
Version: 0.0.5
Summary: A python yolov3-tiny-based object recognizer.
Home-page: http://github.com/ryderdamen/objectdaddy
Author: Ryder Damen
Author-email: dev@ryderdamen.com
License: MIT
Keywords: rtsp stream python
Platform: UNKNOWN
Requires-Dist: opencv-contrib-python (==4.4.0.46)
Requires-Dist: imutils (==0.5.4)
